README.rst
setup.py
django_tasker_exchangerate/__init__.py
django_tasker_exchangerate/admin.py
django_tasker_exchangerate/apps.py
django_tasker_exchangerate/exchangerate.py
django_tasker_exchangerate/models.py
django_tasker_exchangerate/tests.py
django_tasker_exchangerate.egg-info/PKG-INFO
django_tasker_exchangerate.egg-info/SOURCES.txt
django_tasker_exchangerate.egg-info/dependency_links.txt
django_tasker_exchangerate.egg-info/requires.txt
django_tasker_exchangerate.egg-info/top_level.txt
django_tasker_exchangerate/management/__init__.py
django_tasker_exchangerate/management/commands/__init__.py
django_tasker_exchangerate/management/commands/exchangerate.py
django_tasker_exchangerate/migrations/0001_initial.py
django_tasker_exchangerate/migrations/__init__.py
tests/__init__.py
tests/settings.py
tests/test_base.py
tests/urls.py
tests/wsgi.py