Metadata-Version: 1.2
Name: django-tasker-exchangerate
Version: 0.0.2
Summary: Exchange Rates for Django 2.x
Home-page: https://github.com/kostya-ten/django_tasker_exchangerate/
Author: Kostya Ten
Author-email: kostya@yandex.ru
License: Apache License 2.0
Project-URL: Documentation, https://django-tasker-exchange-rate.readthedocs.io/
Project-URL: Source, https://github.com/kostya-ten/django_tasker_exchangerate/
Project-URL: Tracker, https://github.com/kostya-ten/django_tasker_exchangerate/issues
Platform: UNKNOWN
Classifier: Environment :: Web Environment
Classifier: Natural Language :: English
Classifier: Natural Language :: Russian
Classifier: Framework :: Django
Classifier: Framework :: Django :: 2.1
Classifier: Framework :: Django :: 2.2
Classifier: Intended Audience :: Developers
Classifier: Operating System :: OS Independent
Classifier: Programming Language :: Python
Classifier: Programming Language :: Python :: 3.6
Classifier: Programming Language :: Python :: 3.7
Classifier: Programming Language :: Python :: 3.8
Classifier: Topic :: Internet :: WWW/HTTP
Classifier: Topic :: Internet :: WWW/HTTP :: Dynamic Content
Classifier: License :: OSI Approved :: Apache Software License
Requires-Python: >=3
